jupyterhub_saml_auth/__init__.py
jupyterhub_saml_auth/authenticator.py
jupyterhub_saml_auth/handlers.py
test/__init__.py
test/conftest.py
test/jupyterhub_config.py
test/test_acceptance.py
jupyterhub_saml_auth-0.3.2.dist-info/LICENSE
jupyterhub_saml_auth-0.3.2.dist-info/METADATA
jupyterhub_saml_auth-0.3.2.dist-info/WHEEL
jupyterhub_saml_auth-0.3.2.dist-info/top_level.txt
jupyterhub_saml_auth-0.3.2.dist-info/RECORD
