Metadata-Version: 2.1
Name: jupyterhub-saml-auth
Version: 0.3.2
Summary: UNKNOWN
Home-page: https://github.com/ucsd-ets/jupyterhub-saml-auth
Author: Wesley Uykimpang
License: UNKNOWN
Platform: UNKNOWN
Requires-Python: >=3.7.0
License-File: LICENSE
Requires-Dist: python3-saml
Requires-Dist: jupyterhub
Requires-Dist: traitlets (>=5.0.0)
Requires-Dist: notebook
